setup.py
ks/__init__.py
ks/kolmogorov.py
ks.egg-info/PKG-INFO
ks.egg-info/SOURCES.txt
ks.egg-info/dependency_links.txt
ks.egg-info/requires.txt
ks.egg-info/top_level.txt