Metadata-Version: 1.0
Name: ks
Version: 0.1
Summary: kolmogorov schmirnov test
Home-page: https://github.com/jattenberg/ks
Author: josh attenberg
Author-email: jattenbe@stern.nyu.edu
License: Apache 2.0
Platform: UNKNOWN
